loopbot/__init__.py
loopbot/bot.py
loopbot/client.py
loopbot/types.py
loopbot/builders/__init__.py
loopbot/builders/action_row.py
loopbot/builders/button.py
loopbot/builders/container.py
loopbot/builders/embed.py
loopbot/builders/file.py
loopbot/builders/media_gallery.py
loopbot/builders/modal.py
loopbot/builders/section.py
loopbot/builders/select_menu.py
loopbot/builders/separator.py
loopbot/builders/text_display.py
loopbot/context/__init__.py
loopbot/context/base.py
loopbot/context/button.py
loopbot/context/command.py
loopbot/context/modal.py
loopbot/context/select.py
loopbot_discord_sdk-1.0.1.dist-info/METADATA
loopbot_discord_sdk-1.0.1.dist-info/WHEEL
loopbot_discord_sdk-1.0.1.dist-info/top_level.txt
loopbot_discord_sdk-1.0.1.dist-info/RECORD
