Metadata-Version: 2.4
Name: loopbot-discord-sdk
Version: 1.0.1
Summary: Official Loop Discord SDK for Python - Build Discord bots without websockets
Author-email: Loop <contact@loopbot.app>
License: MIT
Project-URL: Homepage, https://loopbot.app
Project-URL: Documentation, https://loopbot.app/docs
Project-URL: Repository, https://github.com/loopbot/python-sdk
Project-URL: Issues, https://github.com/loopbot/python-sdk/issues
Keywords: discord,bot,sdk,loop,loopbot,interactions,slash-commands,buttons,modals
Classifier: Development Status :: 4 - Beta
Classifier: Intended Audience :: Developers
Classifier: License :: OSI Approved :: MIT License
Classifier: Operating System :: OS Independent
Classifier: Programming Language :: Python :: 3
Classifier: Programming Language :: Python :: 3.8
Classifier: Programming Language :: Python :: 3.9
Classifier: Programming Language :: Python :: 3.10
Classifier: Programming Language :: Python :: 3.11
Classifier: Programming Language :: Python :: 3.12
Classifier: Topic :: Communications :: Chat
Classifier: Topic :: Software Development :: Libraries :: Python Modules
Classifier: Typing :: Typed
Requires-Python: >=3.8
Requires-Dist: aiohttp>=3.8.0
Requires-Dist: aiohttp-sse-client>=0.2.1
Provides-Extra: dev
Requires-Dist: pytest>=7.0.0; extra == "dev"
Requires-Dist: pytest-asyncio>=0.21.0; extra == "dev"
Requires-Dist: black>=23.0.0; extra == "dev"
Requires-Dist: mypy>=1.0.0; extra == "dev"
